PyCHAM/PyCHAM.py
PyCHAM/__init__.py
PyCHAM/__main__.py
PyCHAM/accom_coeff_calc.py
PyCHAM/aq_mat_prep.py
PyCHAM/cham_up.py
PyCHAM/coag.py
PyCHAM/compl_evap.py
PyCHAM/def_mod_var.py
PyCHAM/diff_vol_est.py
PyCHAM/dydt_rec.py
PyCHAM/eqn_interr.py
PyCHAM/eqn_pars.py
PyCHAM/fl_reg_determ.py
PyCHAM/formatting.py
PyCHAM/fullmov.py
PyCHAM/init_conc.py
PyCHAM/init_water_partit.py
PyCHAM/jac_setup.py
PyCHAM/jac_up.py
PyCHAM/lamp_photo.py
PyCHAM/middle.py
PyCHAM/mov_cen.py
PyCHAM/mov_cen_water_eq.py
PyCHAM/nuc.py
PyCHAM/ode_solv.py
PyCHAM/ode_solv_wat.py
PyCHAM/ode_updater.py
PyCHAM/part_prop.py
PyCHAM/partit_var.py
PyCHAM/partit_var_prep.py
PyCHAM/photo_num.py
PyCHAM/photolysisRates.py
PyCHAM/plotter.py
PyCHAM/pp_dursim.py
PyCHAM/pp_intro.py
PyCHAM/prop_calc.py
PyCHAM/rate_coeffs.py
PyCHAM/rec.py
PyCHAM/rec_prep.py
PyCHAM/retr_out.py
PyCHAM/reyn_num.py
PyCHAM/rrc_calc.py
PyCHAM/save.py
PyCHAM/sch_interr.py
PyCHAM/size_distr.py
PyCHAM/ui_check.py
PyCHAM/user_input.py
PyCHAM/v_check.py
PyCHAM/volat_calc.py
PyCHAM/wallloss.py
PyCHAM/water_calc.py
PyCHAM/wk_int.py
PyCHAM/write_RO2_indices.py
PyCHAM/write_dydt_rec.py
PyCHAM/write_ode_solv.py
PyCHAM/write_rate_file.py
PyCHAM/xml_interr.py
PyCHAM/zenith.py
PyCHAM/input/apinene_mcm.kpp
PyCHAM/input/example_model_var.txt
PyCHAM/input/example_model_var_inc_aq.txt
PyCHAM/input/example_scheme.txt
PyCHAM/input/example_scheme_inc_aq.kpp
PyCHAM/input/example_xml.xml
PyCHAM/output/GMD_paper_plotting_scripts/fig01_mod_var.txt
PyCHAM/output/GMD_paper_plotting_scripts/fig01_res_plot.py
PyCHAM/output/GMD_paper_plotting_scripts/fig01_scheme.txt
PyCHAM/output/GMD_paper_plotting_scripts/fig03_mod_var_hiNOx.txt
PyCHAM/output/GMD_paper_plotting_scripts/fig03_mod_var_loNOx.txt
PyCHAM/output/GMD_paper_plotting_scripts/fig03_res_plot.py
PyCHAM/output/GMD_paper_plotting_scripts/fig03_scheme.txt
PyCHAM/output/GMD_paper_plotting_scripts/fig04_res_plot.py
PyCHAM/output/GMD_paper_plotting_scripts/fig05_res_plot.py
PyCHAM-2.1.9.dist-info/LICENSE
PyCHAM-2.1.9.dist-info/METADATA
PyCHAM-2.1.9.dist-info/WHEEL
PyCHAM-2.1.9.dist-info/top_level.txt
PyCHAM-2.1.9.dist-info/RECORD
