Metadata-Version: 2.1
Name: PyCHAM
Version: 2.1.9
Summary: PyCHAM: CHemistry with Aerosol Microphysics in Python
Home-page: https://github.com/simonom/PyCHAM
Author: Simon O'Meara
Author-email: simon.omeara@manchester.ac.uk
License: UNKNOWN
Keywords: aerosol,chamber,model
Platform: UNKNOWN
Classifier: Programming Language :: Python :: 3
Classifier: License :: OSI Approved :: GNU General Public License v3 (GPLv3)
Classifier: Operating System :: OS Independent
Requires-Python: >=3.6
Requires-Dist: PyQt5
Requires-Dist: pickleshare
Requires-Dist: numpy
Requires-Dist: backcall
Requires-Dist: certifi
Requires-Dist: cycler
Requires-Dist: decorator
Requires-Dist: gitpython
Requires-Dist: ipdb
Requires-Dist: matplotlib
Requires-Dist: scipy
Requires-Dist: xmltodict
Requires-Dist: requests
